geosdemo_haoyu/__init__.py
geosdemo_haoyu/common.py
geosdemo_haoyu/foliumap.py
geosdemo_haoyu/geosdemo_haoyu.py
geosdemo_haoyu-0.1.0.dist-info/LICENSE
geosdemo_haoyu-0.1.0.dist-info/METADATA
geosdemo_haoyu-0.1.0.dist-info/WHEEL
geosdemo_haoyu-0.1.0.dist-info/dependency_links.txt
geosdemo_haoyu-0.1.0.dist-info/top_level.txt
geosdemo_haoyu-0.1.0.dist-info/RECORD
