Metadata-Version: 2.1
Name: geosdemo-haoyu
Version: 0.1.0
Summary: A python package for interactive mapping.
Home-page: https://github.com/hniu-tamu/geosdemo-haoyu
Author: Haoyu Niu
Author-email: hniu@tamu.edu
License: MIT license
Keywords: geosdemo_haoyu
Classifier: Intended Audience :: Developers
Classifier: License :: OSI Approved :: MIT License
Classifier: Natural Language :: English
Classifier: Programming Language :: Python :: 3
Classifier: Programming Language :: Python :: 3.8
Classifier: Programming Language :: Python :: 3.9
Classifier: Programming Language :: Python :: 3.10
Classifier: Programming Language :: Python :: 3.11
Requires-Python: >=3.8
License-File: LICENSE
Requires-Dist: folium
Requires-Dist: ipyleaflet
Requires-Dist: geopandas
Requires-Dist: httpx
